[
  {
    "model": "auth.user",
    "pk": 2,
    "fields": {
      "password": "pbkdf2_sha256$36000$k8dPrru2cLeP$EEelZJW8yvdCldqU1wj1bcMlVcpsgmoqVRqu8pdQbLI=",
      "last_login": "2018-03-28T01:03:46Z",
      "is_superuser": true,
      "username": "admin",
      "first_name": "Jose",
      "last_name": "Lopez",
      "email": "",
      "is_staff": true,
      "is_active": true,
      "date_joined": "2018-03-17T23:56:29Z",
      "groups": [],
      "user_permissions": []
    }
  },
  {
    "model": "auth.user",
    "pk": 3,
    "fields": {
      "password": "pbkdf2_sha256$36000$yMTFukdktPve$ADU77aQ1YDcfu5nhvEmtkVjxzvmHPfUdRJmdaudmKmU=",
      "last_login": null,
      "is_superuser": false,
      "username": "DDeaneNone",
      "first_name": "Dalis",
      "last_name": "Deane",
      "email": "",
      "is_staff": false,
      "is_active": true,
      "date_joined": "2018-03-28T01:07:03.421Z",
      "groups": [
        1
      ],
      "user_permissions": []
    }
  },
  {
    "model": "auth.user",
    "pk": 4,
    "fields": {
      "password": "pbkdf2_sha256$36000$j6ytFIZSf0CL$BxBGhMCF+mCAhnz7G4dC3vFgbUaXTjUxE1fzS7TYyHc=",
      "last_login": null,
      "is_superuser": false,
      "username": "MDomenicoNone",
      "first_name": "Mace",
      "last_name": "Domenico",
      "email": "",
      "is_staff": false,
      "is_active": true,
      "date_joined": "2018-03-28T01:07:03.604Z",
      "groups": [
        1
      ],
      "user_permissions": []
    }
  },
  {
    "model": "auth.user",
    "pk": 5,
    "fields": {
      "password": "pbkdf2_sha256$36000$Vi8Hxb2WpSAB$XkEniyfXBcYxuP5jCHLMM5bgvianHB62M/h3B+b3Fn0=",
      "last_login": null,
      "is_superuser": false,
      "username": "NBrookeNone",
      "first_name": "Neille",
      "last_name": "Brooke",
      "email": "",
      "is_staff": false,
      "is_active": true,
      "date_joined": "2018-03-28T01:07:03.699Z",
      "groups": [
        1
      ],
      "user_permissions": []
    }
  },
  {
    "model": "auth.user",
    "pk": 6,
    "fields": {
      "password": "pbkdf2_sha256$36000$fF4Ei9XZonvc$tXzz14ctsCw+Xoo2nAY50W8ou3GQaHKzn6DJyEhyTSk=",
      "last_login": null,
      "is_superuser": false,
      "username": "WChildNone",
      "first_name": "Welsh",
      "last_name": "Child",
      "email": "",
      "is_staff": false,
      "is_active": true,
      "date_joined": "2018-03-28T01:07:03.763Z",
      "groups": [
        1
      ],
      "user_permissions": []
    }
  },
  {
    "model": "auth.user",
    "pk": 7,
    "fields": {
      "password": "pbkdf2_sha256$36000$tPb4mP9AA2LA$EWAN6NFs/JAt/6TWthZ3+/jCA8RCB2WdfEHvKwR+P1w=",
      "last_login": null,
      "is_superuser": false,
      "username": "NJermyNone",
      "first_name": "Nadiya",
      "last_name": "Jermy",
      "email": "",
      "is_staff": false,
      "is_active": true,
      "date_joined": "2018-03-28T01:07:03.840Z",
      "groups": [
        1
      ],
      "user_permissions": []
    }
  },
  {
    "model": "auth.user",
    "pk": 8,
    "fields": {
      "password": "pbkdf2_sha256$36000$2flbqs55RJ5S$SHC2P9lbKELVAeE9Q1OLeAev7PekEfpQmiGV9FeQX4U=",
      "last_login": null,
      "is_superuser": false,
      "username": "KToweNone",
      "first_name": "Kath",
      "last_name": "Towe",
      "email": "",
      "is_staff": false,
      "is_active": true,
      "date_joined": "2018-03-28T01:07:03.912Z",
      "groups": [
        1
      ],
      "user_permissions": []
    }
  },
  {
    "model": "auth.user",
    "pk": 9,
    "fields": {
      "password": "pbkdf2_sha256$36000$py0mRj46T1rP$6N4OPuHFzWiZ5wMZnR944i0S78XuqYPi87wtfM8Y6zE=",
      "last_login": null,
      "is_superuser": false,
      "username": "CFerrucciNone",
      "first_name": "Colin",
      "last_name": "Ferrucci",
      "email": "",
      "is_staff": false,
      "is_active": true,
      "date_joined": "2018-03-28T01:07:03.992Z",
      "groups": [
        1
      ],
      "user_permissions": []
    }
  },
  {
    "model": "auth.user",
    "pk": 10,
    "fields": {
      "password": "pbkdf2_sha256$36000$LXfcgAkUeSbM$nvkPsDsIAMywecM87uLCLAMAQMvOXMmjBdxadQB/bik=",
      "last_login": null,
      "is_superuser": false,
      "username": "CJeanonNone",
      "first_name": "Cassondra",
      "last_name": "Jeanon",
      "email": "",
      "is_staff": false,
      "is_active": true,
      "date_joined": "2018-03-28T01:07:04.057Z",
      "groups": [
        1
      ],
      "user_permissions": []
    }
  },
  {
    "model": "auth.user",
    "pk": 11,
    "fields": {
      "password": "pbkdf2_sha256$36000$dVzzgRlRoBGH$TQM3XFLKXAy+93BZ3XObp/qgmMMAfiW0rx6LpHlu7+4=",
      "last_login": null,
      "is_superuser": false,
      "username": "ZVardenNone",
      "first_name": "Zia",
      "last_name": "Varden",
      "email": "",
      "is_staff": false,
      "is_active": true,
      "date_joined": "2018-03-28T01:07:04.124Z",
      "groups": [
        1
      ],
      "user_permissions": []
    }
  },
  {
    "model": "auth.user",
    "pk": 12,
    "fields": {
      "password": "pbkdf2_sha256$36000$V3iMKaYhphvx$g2I3uOmpYzhnIio1O+MAk7W3BV+Ij/FVijfkW2vXj/Q=",
      "last_login": null,
      "is_superuser": false,
      "username": "DWyonNone",
      "first_name": "Davin",
      "last_name": "Wyon",
      "email": "",
      "is_staff": false,
      "is_active": true,
      "date_joined": "2018-03-28T01:07:04.198Z",
      "groups": [
        1
      ],
      "user_permissions": []
    }
  },
  {
    "model": "auth.user",
    "pk": 13,
    "fields": {
      "password": "pbkdf2_sha256$36000$BGmYz0aCm8mt$W9yX44QVw0AAv95a1l93dRBaQAF9lSeMTuXpQhto+pU=",
      "last_login": null,
      "is_superuser": false,
      "username": "NHeballNone",
      "first_name": "Nikolia",
      "last_name": "Heball",
      "email": "",
      "is_staff": false,
      "is_active": true,
      "date_joined": "2018-03-28T01:07:04.273Z",
      "groups": [
        1
      ],
      "user_permissions": []
    }
  },
  {
    "model": "auth.user",
    "pk": 14,
    "fields": {
      "password": "pbkdf2_sha256$36000$CDp6c2Bk99nE$fx1tOkXPLKYapbIuFeUm0XsxJUq5pQRLpYETuLn2MMA=",
      "last_login": null,
      "is_superuser": false,
      "username": "PCruxtonNone",
      "first_name": "Padraig",
      "last_name": "Cruxton",
      "email": "",
      "is_staff": false,
      "is_active": true,
      "date_joined": "2018-03-28T01:07:04.343Z",
      "groups": [
        1
      ],
      "user_permissions": []
    }
  },
  {
    "model": "auth.user",
    "pk": 15,
    "fields": {
      "password": "pbkdf2_sha256$36000$bLVvl8arHXG2$K1K1loKfekS0TEkQL4xjJqfhwSKVdSDhEmYLYUaBpKI=",
      "last_login": null,
      "is_superuser": false,
      "username": "MPulferNone",
      "first_name": "Matilda",
      "last_name": "Pulfer",
      "email": "",
      "is_staff": false,
      "is_active": true,
      "date_joined": "2018-03-28T01:07:04.415Z",
      "groups": [
        1
      ],
      "user_permissions": []
    }
  },
  {
    "model": "auth.user",
    "pk": 16,
    "fields": {
      "password": "pbkdf2_sha256$36000$a5CilKhuMiGR$m8Xto8+uj+Q/b4thuryNrWHdYjyPQENM2BJvEHtn61A=",
      "last_login": null,
      "is_superuser": false,
      "username": "LBasillNone",
      "first_name": "Leonard",
      "last_name": "Basill",
      "email": "",
      "is_staff": false,
      "is_active": true,
      "date_joined": "2018-03-28T01:07:04.490Z",
      "groups": [
        1
      ],
      "user_permissions": []
    }
  },
  {
    "model": "auth.user",
    "pk": 17,
    "fields": {
      "password": "pbkdf2_sha256$36000$9w1CAROd8dUm$fEnjqYKsmDd5/c7+ydVIKxDa8uaeWH3Cg742IQTwSnQ=",
      "last_login": null,
      "is_superuser": false,
      "username": "GLutschNone",
      "first_name": "Gaelan",
      "last_name": "Lutsch",
      "email": "",
      "is_staff": false,
      "is_active": true,
      "date_joined": "2018-03-28T01:07:04.553Z",
      "groups": [
        1
      ],
      "user_permissions": []
    }
  },
  {
    "model": "auth.user",
    "pk": 18,
    "fields": {
      "password": "pbkdf2_sha256$36000$a3Gv3DWtcixg$k2iZ1ONbogFxSk+ViMUplVflb2KdzixI6oGnjMYCxdQ=",
      "last_login": null,
      "is_superuser": false,
      "username": "EGrevesonNone",
      "first_name": "Everett",
      "last_name": "Greveson",
      "email": "",
      "is_staff": false,
      "is_active": true,
      "date_joined": "2018-03-28T01:07:04.619Z",
      "groups": [
        1
      ],
      "user_permissions": []
    }
  },
  {
    "model": "auth.user",
    "pk": 19,
    "fields": {
      "password": "pbkdf2_sha256$36000$3NfZROw69hed$aW9RpV3fW2kIGCmW4GL7QM8DYoNA+MR1yi3UPYSaTMQ=",
      "last_login": null,
      "is_superuser": false,
      "username": "MElphickNone",
      "first_name": "Murry",
      "last_name": "Elphick",
      "email": "",
      "is_staff": false,
      "is_active": true,
      "date_joined": "2018-03-28T01:07:04.684Z",
      "groups": [
        1
      ],
      "user_permissions": []
    }
  },
  {
    "model": "auth.user",
    "pk": 20,
    "fields": {
      "password": "pbkdf2_sha256$36000$JPeD83TMCGJq$7SHuGPjUZtLE+sKHDYvh64XC/EIvhVoEQeUh9XFJOpo=",
      "last_login": null,
      "is_superuser": false,
      "username": "DReayNone",
      "first_name": "Daisy",
      "last_name": "Reay",
      "email": "",
      "is_staff": false,
      "is_active": true,
      "date_joined": "2018-03-28T01:07:04.759Z",
      "groups": [
        1
      ],
      "user_permissions": []
    }
  },
  {
    "model": "auth.user",
    "pk": 21,
    "fields": {
      "password": "pbkdf2_sha256$36000$wJcg88xN29kK$orp2VqFJuQftL2mVQEqef7C2VUL0VKo8HKX3AU7vnQM=",
      "last_login": null,
      "is_superuser": false,
      "username": "JDuffilNone",
      "first_name": "Julian",
      "last_name": "Duffil",
      "email": "",
      "is_staff": false,
      "is_active": true,
      "date_joined": "2018-03-28T01:07:04.817Z",
      "groups": [
        1
      ],
      "user_permissions": []
    }
  },
  {
    "model": "auth.user",
    "pk": 22,
    "fields": {
      "password": "pbkdf2_sha256$36000$157ryytKYD2k$srx7TwNpHpolqmdxsFKzdAw/cawdTl1BvEiq16LAHw8=",
      "last_login": null,
      "is_superuser": false,
      "username": "RSkainsNone",
      "first_name": "Rudiger",
      "last_name": "Skains",
      "email": "",
      "is_staff": false,
      "is_active": true,
      "date_joined": "2018-03-28T01:07:04.888Z",
      "groups": [
        1
      ],
      "user_permissions": []
    }
  },
  {
    "model": "auth.user",
    "pk": 23,
    "fields": {
      "password": "pbkdf2_sha256$36000$7cZnPPTrlqYy$CNs6bqwKt7vdEIVrSoEesiv+bDmqhbTmO/3EyRtjqaY=",
      "last_login": null,
      "is_superuser": false,
      "username": "CLubeNone",
      "first_name": "Carmon",
      "last_name": "Lube",
      "email": "",
      "is_staff": false,
      "is_active": true,
      "date_joined": "2018-03-28T01:07:04.951Z",
      "groups": [
        1
      ],
      "user_permissions": []
    }
  },
  {
    "model": "auth.user",
    "pk": 24,
    "fields": {
      "password": "pbkdf2_sha256$36000$1HXz2z4hWTzj$0pLkFee9lGoDQUyyj/QT6WFJYc09S5XAkkbBsh6ZV9k=",
      "last_login": null,
      "is_superuser": false,
      "username": "ABallendineNone",
      "first_name": "Aime",
      "last_name": "Ballendine",
      "email": "",
      "is_staff": false,
      "is_active": true,
      "date_joined": "2018-03-28T01:07:05.011Z",
      "groups": [
        1
      ],
      "user_permissions": []
    }
  },
  {
    "model": "auth.user",
    "pk": 25,
    "fields": {
      "password": "pbkdf2_sha256$36000$vFoROYFozQ2K$KRXsPTTvBxMV7uYfeJ7c9YR70Oa/6ARaBZqjl6n+IUg=",
      "last_login": null,
      "is_superuser": false,
      "username": "CPietzkerNone",
      "first_name": "Charlot",
      "last_name": "Pietzker",
      "email": "",
      "is_staff": false,
      "is_active": true,
      "date_joined": "2018-03-28T01:07:05.069Z",
      "groups": [
        1
      ],
      "user_permissions": []
    }
  },
  {
    "model": "auth.user",
    "pk": 26,
    "fields": {
      "password": "pbkdf2_sha256$36000$ll0N5ry8TLOk$MfrzY1nMeLgfemRuvNzXMuPoLz1OLD0ppow0NFUxW5I=",
      "last_login": null,
      "is_superuser": false,
      "username": "MDrewNone",
      "first_name": "Millicent",
      "last_name": "Drew",
      "email": "",
      "is_staff": false,
      "is_active": true,
      "date_joined": "2018-03-28T01:07:05.139Z",
      "groups": [
        1
      ],
      "user_permissions": []
    }
  },
  {
    "model": "auth.user",
    "pk": 27,
    "fields": {
      "password": "pbkdf2_sha256$36000$WCVEqN0BrtfS$6/eASywg/cbVOcmshOTGbDZ9auc0vzDzUOHTCF9i9xc=",
      "last_login": null,
      "is_superuser": false,
      "username": "MMalinowskiNone",
      "first_name": "Maritsa",
      "last_name": "Malinowski",
      "email": "",
      "is_staff": false,
      "is_active": true,
      "date_joined": "2018-03-28T01:07:05.198Z",
      "groups": [
        1
      ],
      "user_permissions": []
    }
  },
  {
    "model": "auth.user",
    "pk": 28,
    "fields": {
      "password": "pbkdf2_sha256$36000$tFP1Ysqilf0d$oi4SzSC/qOGKPQAAlgLxEMy17L6TPjXvHUfKwGh/Ons=",
      "last_login": null,
      "is_superuser": false,
      "username": "KBoulesNone",
      "first_name": "Karlyn",
      "last_name": "Boules",
      "email": "",
      "is_staff": false,
      "is_active": true,
      "date_joined": "2018-03-28T01:07:05.269Z",
      "groups": [
        1
      ],
      "user_permissions": []
    }
  },
  {
    "model": "auth.user",
    "pk": 29,
    "fields": {
      "password": "pbkdf2_sha256$36000$7Qm2nyAipq0i$mz65njVJNvJ0MF9B6lrcAdB/J2RSbr3/9MZ1o2MSVRo=",
      "last_login": null,
      "is_superuser": false,
      "username": "JClendinningNone",
      "first_name": "Johann",
      "last_name": "Clendinning",
      "email": "",
      "is_staff": false,
      "is_active": true,
      "date_joined": "2018-03-28T01:07:05.339Z",
      "groups": [
        1
      ],
      "user_permissions": []
    }
  },
  {
    "model": "auth.user",
    "pk": 30,
    "fields": {
      "password": "pbkdf2_sha256$36000$YFc4M229SJvC$LjDDgAza+fCel7M+nqbAB3zcfMX1ttbkUmXMGytX/d4=",
      "last_login": null,
      "is_superuser": false,
      "username": "VDewsNone",
      "first_name": "Vachel",
      "last_name": "Dews",
      "email": "",
      "is_staff": false,
      "is_active": true,
      "date_joined": "2018-03-28T01:07:05.408Z",
      "groups": [
        1
      ],
      "user_permissions": []
    }
  },
  {
    "model": "auth.user",
    "pk": 31,
    "fields": {
      "password": "pbkdf2_sha256$36000$TxUYCPxt3uYe$qxX4AWK+iVBThcpn8cjWluXfCJR2iZEcVoeQ36nOM1Y=",
      "last_login": null,
      "is_superuser": false,
      "username": "FFendtNone",
      "first_name": "Felix",
      "last_name": "Fendt",
      "email": "",
      "is_staff": false,
      "is_active": true,
      "date_joined": "2018-03-28T01:07:05.490Z",
      "groups": [
        1
      ],
      "user_permissions": []
    }
  },
  {
    "model": "auth.user",
    "pk": 32,
    "fields": {
      "password": "pbkdf2_sha256$36000$8h8wJrYWgMRf$+7mgttpDYnhQ9xdoxswnWDw1PpYyQ1Okk/ZXORUSl4k=",
      "last_login": null,
      "is_superuser": false,
      "username": "LHolhouseNone",
      "first_name": "Liana",
      "last_name": "Holhouse",
      "email": "",
      "is_staff": false,
      "is_active": true,
      "date_joined": "2018-03-28T01:07:05.551Z",
      "groups": [
        1
      ],
      "user_permissions": []
    }
  },
  {
    "model": "auth.user",
    "pk": 33,
    "fields": {
      "password": "pbkdf2_sha256$36000$9IxeuhF1ZbzA$QjecFBJqQLeEQj4K/yE1/mHv4Rq4XCQ7E8fqX+ft328=",
      "last_login": null,
      "is_superuser": false,
      "username": "ACarrenNone",
      "first_name": "Antonia",
      "last_name": "Carren",
      "email": "",
      "is_staff": false,
      "is_active": true,
      "date_joined": "2018-03-28T01:07:05.609Z",
      "groups": [
        1
      ],
      "user_permissions": []
    }
  },
  {
    "model": "auth.user",
    "pk": 34,
    "fields": {
      "password": "pbkdf2_sha256$36000$cRboDKmQyW1x$iD9US7PVkPhkvm5mGjVnKFo+iNfEUO/jqJCtpz8hsWI=",
      "last_login": null,
      "is_superuser": false,
      "username": "CHadcroftNone",
      "first_name": "Clari",
      "last_name": "Hadcroft",
      "email": "",
      "is_staff": false,
      "is_active": true,
      "date_joined": "2018-03-28T01:07:05.668Z",
      "groups": [
        1
      ],
      "user_permissions": []
    }
  },
  {
    "model": "auth.user",
    "pk": 35,
    "fields": {
      "password": "pbkdf2_sha256$36000$hxSQM3wzstSQ$NMYJ02NqnUZjsMuS1yoThO/VGeegqk19xKYkqRMpSwA=",
      "last_login": null,
      "is_superuser": false,
      "username": "EAnniesNone",
      "first_name": "Eartha",
      "last_name": "Annies",
      "email": "",
      "is_staff": false,
      "is_active": true,
      "date_joined": "2018-03-28T01:07:05.739Z",
      "groups": [
        1
      ],
      "user_permissions": []
    }
  },
  {
    "model": "auth.user",
    "pk": 36,
    "fields": {
      "password": "pbkdf2_sha256$36000$6d0CidJw3Rks$YymBl5oe2N6Tyhzjc8N0DumTt2PVzVsw2JitKmtFnNw=",
      "last_login": null,
      "is_superuser": false,
      "username": "NBarrattNone",
      "first_name": "Nichols",
      "last_name": "Barratt",
      "email": "",
      "is_staff": false,
      "is_active": true,
      "date_joined": "2018-03-28T01:07:05.846Z",
      "groups": [
        1
      ],
      "user_permissions": []
    }
  },
  {
    "model": "auth.user",
    "pk": 37,
    "fields": {
      "password": "pbkdf2_sha256$36000$pCnXRKXiSWcY$WCx8xKueSMBM6x6Lq0g92dNHsaesWmQDzvsq/7MmE4Q=",
      "last_login": null,
      "is_superuser": false,
      "username": "HKaliszewskiNone",
      "first_name": "Harrison",
      "last_name": "Kaliszewski",
      "email": "",
      "is_staff": false,
      "is_active": true,
      "date_joined": "2018-03-28T01:07:05.915Z",
      "groups": [
        1
      ],
      "user_permissions": []
    }
  },
  {
    "model": "auth.user",
    "pk": 38,
    "fields": {
      "password": "pbkdf2_sha256$36000$gpQGhuAD4s5T$K0t15yovKWSOcPTlIg9inj0Yo+hB5iNJBX8lrNbDTHU=",
      "last_login": null,
      "is_superuser": false,
      "username": "LDamantNone",
      "first_name": "Linnell",
      "last_name": "Damant",
      "email": "",
      "is_staff": false,
      "is_active": true,
      "date_joined": "2018-03-28T01:07:05.983Z",
      "groups": [
        1
      ],
      "user_permissions": []
    }
  },
  {
    "model": "auth.user",
    "pk": 39,
    "fields": {
      "password": "pbkdf2_sha256$36000$3xXaQEVhIkq0$BF2V1mdXT8ZSbMrvJQV3B7QLQpNg4UVV2QP98IBwngY=",
      "last_login": null,
      "is_superuser": false,
      "username": "RCattNone",
      "first_name": "Reeta",
      "last_name": "Catt",
      "email": "",
      "is_staff": false,
      "is_active": true,
      "date_joined": "2018-03-28T01:07:06.056Z",
      "groups": [
        1
      ],
      "user_permissions": []
    }
  },
  {
    "model": "auth.user",
    "pk": 40,
    "fields": {
      "password": "pbkdf2_sha256$36000$9BFpAPZgA72V$rCXYG+E9g/axSg0O4OPpnRkr9YBNeEiWo30By+PakQk=",
      "last_login": null,
      "is_superuser": false,
      "username": "TShintonNone",
      "first_name": "Thaine",
      "last_name": "Shinton",
      "email": "",
      "is_staff": false,
      "is_active": true,
      "date_joined": "2018-03-28T01:07:06.123Z",
      "groups": [
        1
      ],
      "user_permissions": []
    }
  },
  {
    "model": "auth.user",
    "pk": 41,
    "fields": {
      "password": "pbkdf2_sha256$36000$H3oGtUZnTF2t$twIaEtwRX1JrtywE1kCiwPOdzGWTA17ml8gubyqkJwc=",
      "last_login": null,
      "is_superuser": false,
      "username": "RSmailsNone",
      "first_name": "Ravid",
      "last_name": "Smails",
      "email": "",
      "is_staff": false,
      "is_active": true,
      "date_joined": "2018-03-28T01:07:06.208Z",
      "groups": [
        1
      ],
      "user_permissions": []
    }
  },
  {
    "model": "auth.user",
    "pk": 42,
    "fields": {
      "password": "pbkdf2_sha256$36000$x8N2G4VTAi4j$01A4ECeFWIN3p09jiNvuehKJT9q6lYMWBtubjb+Q1Uk=",
      "last_login": null,
      "is_superuser": false,
      "username": "TClymerNone",
      "first_name": "Teddy",
      "last_name": "Clymer",
      "email": "",
      "is_staff": false,
      "is_active": true,
      "date_joined": "2018-03-28T01:07:06.275Z",
      "groups": [
        1
      ],
      "user_permissions": []
    }
  },
  {
    "model": "auth.user",
    "pk": 43,
    "fields": {
      "password": "pbkdf2_sha256$36000$b1tbj25VPXlw$lG3KmwseCxFfbvjFsTO2rT6OFYiHqAAOQVNo/NRpRvw=",
      "last_login": null,
      "is_superuser": false,
      "username": "RSideyNone",
      "first_name": "Rosaleen",
      "last_name": "Sidey",
      "email": "",
      "is_staff": false,
      "is_active": true,
      "date_joined": "2018-03-28T01:07:06.372Z",
      "groups": [
        1
      ],
      "user_permissions": []
    }
  },
  {
    "model": "auth.user",
    "pk": 44,
    "fields": {
      "password": "pbkdf2_sha256$36000$OpCDCjDGCTfw$7LlF9zc5DsHx3tEzHYBpJ06823aH6UoKbU1GcXJbnOw=",
      "last_login": null,
      "is_superuser": false,
      "username": "NCurnockNone",
      "first_name": "Nana",
      "last_name": "Curnock",
      "email": "",
      "is_staff": false,
      "is_active": true,
      "date_joined": "2018-03-28T01:07:06.445Z",
      "groups": [
        1
      ],
      "user_permissions": []
    }
  },
  {
    "model": "auth.user",
    "pk": 45,
    "fields": {
      "password": "pbkdf2_sha256$36000$9jeHBBI5YKdL$uD3qTlJ8lX9iGVbNVyMhaIeePP9hsZTp+EtWxIhDew4=",
      "last_login": null,
      "is_superuser": false,
      "username": "GCreadyNone",
      "first_name": "Geno",
      "last_name": "Cready",
      "email": "",
      "is_staff": false,
      "is_active": true,
      "date_joined": "2018-03-28T01:07:06.519Z",
      "groups": [
        1
      ],
      "user_permissions": []
    }
  },
  {
    "model": "auth.user",
    "pk": 46,
    "fields": {
      "password": "pbkdf2_sha256$36000$mfXRiLP39NHR$HcC2qrtlPfa4fAaLLbpSK24Fisu/Yfp2KBQ5PtXa3hs=",
      "last_login": null,
      "is_superuser": false,
      "username": "KRungeNone",
      "first_name": "Karlie",
      "last_name": "Runge",
      "email": "",
      "is_staff": false,
      "is_active": true,
      "date_joined": "2018-03-28T01:07:06.591Z",
      "groups": [
        1
      ],
      "user_permissions": []
    }
  },
  {
    "model": "auth.user",
    "pk": 47,
    "fields": {
      "password": "pbkdf2_sha256$36000$YKfRyZjTIhos$ZUfwxwjh867wt2ZOnL79tIIEncw+WyuSR8pnxAovNZc=",
      "last_login": null,
      "is_superuser": false,
      "username": "GEdlynNone",
      "first_name": "Gypsy",
      "last_name": "Edlyn",
      "email": "",
      "is_staff": false,
      "is_active": true,
      "date_joined": "2018-03-28T01:07:06.652Z",
      "groups": [
        1
      ],
      "user_permissions": []
    }
  },
  {
    "model": "auth.user",
    "pk": 48,
    "fields": {
      "password": "pbkdf2_sha256$36000$BXhF8lgUiDiZ$ATnpjlZ6b7Djbpy+vzoqGqVd5nQscxMLptUvAM4/8i0=",
      "last_login": null,
      "is_superuser": false,
      "username": "ULangleyNone",
      "first_name": "Ulick",
      "last_name": "Langley",
      "email": "",
      "is_staff": false,
      "is_active": true,
      "date_joined": "2018-03-28T01:07:06.714Z",
      "groups": [
        1
      ],
      "user_permissions": []
    }
  },
  {
    "model": "auth.user",
    "pk": 49,
    "fields": {
      "password": "pbkdf2_sha256$36000$ZAYLIbqBqL21$5acMt6AWMkQyj7TIMN1wgUhTR4MFuBRJvhR6l3dTKMs=",
      "last_login": null,
      "is_superuser": false,
      "username": "JQuarrieNone",
      "first_name": "Jewell",
      "last_name": "Quarrie",
      "email": "",
      "is_staff": false,
      "is_active": true,
      "date_joined": "2018-03-28T01:07:06.810Z",
      "groups": [
        1
      ],
      "user_permissions": []
    }
  },
  {
    "model": "auth.user",
    "pk": 50,
    "fields": {
      "password": "pbkdf2_sha256$36000$FkAbELAGhPKr$/bkYjvaDfOz7uER7KcOynciZ/C3kv/5AN87m5l2f7j4=",
      "last_login": null,
      "is_superuser": false,
      "username": "SPurvesNone",
      "first_name": "Sidonia",
      "last_name": "Purves",
      "email": "",
      "is_staff": false,
      "is_active": true,
      "date_joined": "2018-03-28T01:07:06.885Z",
      "groups": [
        1
      ],
      "user_permissions": []
    }
  },
  {
    "model": "auth.user",
    "pk": 51,
    "fields": {
      "password": "pbkdf2_sha256$36000$SNblBQy5sIm0$O4Ndun9YPWZp70+BM8Z2MMjwyJXSKMJnYTTP20HFzak=",
      "last_login": null,
      "is_superuser": false,
      "username": "ZMintoNone",
      "first_name": "Zorina",
      "last_name": "Minto",
      "email": "",
      "is_staff": false,
      "is_active": true,
      "date_joined": "2018-03-28T01:07:06.949Z",
      "groups": [
        1
      ],
      "user_permissions": []
    }
  },
  {
    "model": "auth.user",
    "pk": 52,
    "fields": {
      "password": "pbkdf2_sha256$36000$M4o3AAuE3S5J$AWsqRLEiLQfzFVORGxFlCGYwaX8yS7JDBkiPJThiRVc=",
      "last_login": null,
      "is_superuser": false,
      "username": "JBaystonNone",
      "first_name": "Joann",
      "last_name": "Bayston",
      "email": "",
      "is_staff": false,
      "is_active": true,
      "date_joined": "2018-03-28T01:07:07.010Z",
      "groups": [
        1
      ],
      "user_permissions": []
    }
  },
  {
    "model": "auth.user",
    "pk": 53,
    "fields": {
      "password": "pbkdf2_sha256$36000$ZHb6IMqHeVya$M2S3jZ1X1rvMMc8Kg9N2kCWtw1W69hEd6KqlWt65gLw=",
      "last_login": null,
      "is_superuser": false,
      "username": "SAntonoczykNone",
      "first_name": "Sheff",
      "last_name": "Antonoczyk",
      "email": "",
      "is_staff": false,
      "is_active": true,
      "date_joined": "2018-03-28T01:07:07.072Z",
      "groups": [
        1
      ],
      "user_permissions": []
    }
  },
  {
    "model": "auth.user",
    "pk": 54,
    "fields": {
      "password": "pbkdf2_sha256$36000$eeuEp9cqsCwh$BIzgiIDZQDTXeSadXQUKA09OuY/VW+8Nyt0yrEg1qbY=",
      "last_login": null,
      "is_superuser": false,
      "username": "SWillgooseNone",
      "first_name": "Storm",
      "last_name": "Willgoose",
      "email": "",
      "is_staff": false,
      "is_active": true,
      "date_joined": "2018-03-28T01:07:07.134Z",
      "groups": [
        1
      ],
      "user_permissions": []
    }
  },
  {
    "model": "auth.user",
    "pk": 55,
    "fields": {
      "password": "pbkdf2_sha256$36000$JNh9ZVJ9n5mX$ajN+Fj1yIjWTD64Ohe3VkfjG4MPvWE/B2ko9E3kxajo=",
      "last_login": null,
      "is_superuser": false,
      "username": "JAgglioneNone",
      "first_name": "Jamie",
      "last_name": "Agglione",
      "email": "",
      "is_staff": false,
      "is_active": true,
      "date_joined": "2018-03-28T01:07:07.208Z",
      "groups": [
        1
      ],
      "user_permissions": []
    }
  },
  {
    "model": "auth.user",
    "pk": 56,
    "fields": {
      "password": "pbkdf2_sha256$36000$yauDw7RSsld4$XHZxCHkkWCzIjLEXiIQXev9dHfkdvhyka5fGiQXmMkU=",
      "last_login": null,
      "is_superuser": false,
      "username": "GKennardNone",
      "first_name": "Goldy",
      "last_name": "Kennard",
      "email": "",
      "is_staff": false,
      "is_active": true,
      "date_joined": "2018-03-28T01:07:07.274Z",
      "groups": [
        1
      ],
      "user_permissions": []
    }
  },
  {
    "model": "auth.user",
    "pk": 57,
    "fields": {
      "password": "pbkdf2_sha256$36000$BlpR6ZURUFr9$qylSTngbfXIujDUHtJ4wYMMLD/DRVf9NJoO95Y8i9rM=",
      "last_login": null,
      "is_superuser": false,
      "username": "WCaddensNone",
      "first_name": "Wash",
      "last_name": "Caddens",
      "email": "",
      "is_staff": false,
      "is_active": true,
      "date_joined": "2018-03-28T01:07:07.347Z",
      "groups": [
        1
      ],
      "user_permissions": []
    }
  },
  {
    "model": "auth.user",
    "pk": 58,
    "fields": {
      "password": "pbkdf2_sha256$36000$GUtIek47acnX$d54hx0haHU6t74BZFti7Zej2KntnVYG6BrUM0rfHlt4=",
      "last_login": null,
      "is_superuser": false,
      "username": "JRennicksNone",
      "first_name": "Jennifer",
      "last_name": "Rennicks",
      "email": "",
      "is_staff": false,
      "is_active": true,
      "date_joined": "2018-03-28T01:07:07.418Z",
      "groups": [
        1
      ],
      "user_permissions": []
    }
  },
  {
    "model": "auth.user",
    "pk": 59,
    "fields": {
      "password": "pbkdf2_sha256$36000$ryyVHUdi4oh9$fq1wAKuc9GAh1kyT1BmbWJ9rEpZpBZ5Q5RI1Vsgsftc=",
      "last_login": null,
      "is_superuser": false,
      "username": "TMcRamseyNone",
      "first_name": "Tanya",
      "last_name": "McRamsey",
      "email": "",
      "is_staff": false,
      "is_active": true,
      "date_joined": "2018-03-28T01:07:07.481Z",
      "groups": [
        1
      ],
      "user_permissions": []
    }
  },
  {
    "model": "auth.user",
    "pk": 60,
    "fields": {
      "password": "pbkdf2_sha256$36000$6CBanaFlY5yt$VB6/aQfH7EJ3936n2PwZ6xl65eOKDSRypjglODuqyIE=",
      "last_login": null,
      "is_superuser": false,
      "username": "JIngolottiNone",
      "first_name": "Jemima",
      "last_name": "Ingolotti",
      "email": "",
      "is_staff": false,
      "is_active": true,
      "date_joined": "2018-03-28T01:07:07.545Z",
      "groups": [
        1
      ],
      "user_permissions": []
    }
  },
  {
    "model": "auth.user",
    "pk": 61,
    "fields": {
      "password": "pbkdf2_sha256$36000$15Ae1HmZ4tfy$c5JPcmjjFmVpR+9KD9ERFFVaV5FWuqXU1vpqPkLQ41I=",
      "last_login": null,
      "is_superuser": false,
      "username": "AZottoliNone",
      "first_name": "Aldis",
      "last_name": "Zottoli",
      "email": "",
      "is_staff": false,
      "is_active": true,
      "date_joined": "2018-03-28T01:07:07.605Z",
      "groups": [
        1
      ],
      "user_permissions": []
    }
  },
  {
    "model": "auth.user",
    "pk": 62,
    "fields": {
      "password": "pbkdf2_sha256$36000$E6bV0FGnBNyz$Hl5Oj/mDVQCOstuEihqzc+WGaPEi6VQhN5MCItmIQn4=",
      "last_login": null,
      "is_superuser": false,
      "username": "LDamettiNone",
      "first_name": "Lindy",
      "last_name": "Dametti",
      "email": "",
      "is_staff": false,
      "is_active": true,
      "date_joined": "2018-03-28T01:07:07.665Z",
      "groups": [
        1
      ],
      "user_permissions": []
    }
  },
  {
    "model": "auth.user",
    "pk": 63,
    "fields": {
      "password": "pbkdf2_sha256$36000$ji3FNTVMn2pc$JhqXC20zDq/jObnZEWshZU/LJzMoN4Hoxt+pr51yado=",
      "last_login": null,
      "is_superuser": false,
      "username": "CHazeldeanNone",
      "first_name": "Christiana",
      "last_name": "Hazeldean",
      "email": "",
      "is_staff": false,
      "is_active": true,
      "date_joined": "2018-03-28T01:07:07.728Z",
      "groups": [
        1
      ],
      "user_permissions": []
    }
  },
  {
    "model": "auth.user",
    "pk": 64,
    "fields": {
      "password": "pbkdf2_sha256$36000$YcV3U3nv2qxP$Anhc0YO5ZsgX881MCiRvv4pjQXlhJNXdIg479fXbE1k=",
      "last_login": null,
      "is_superuser": false,
      "username": "DMahargNone",
      "first_name": "Dasie",
      "last_name": "Maharg",
      "email": "",
      "is_staff": false,
      "is_active": true,
      "date_joined": "2018-03-28T01:07:07.789Z",
      "groups": [
        1
      ],
      "user_permissions": []
    }
  },
  {
    "model": "auth.user",
    "pk": 65,
    "fields": {
      "password": "pbkdf2_sha256$36000$Rj4sLda9fkWC$CE5GpjfGd0gQ/+oTOoFi31tjtL+7Tpvp0JDBB2zYqco=",
      "last_login": null,
      "is_superuser": false,
      "username": "EMcQuirterNone",
      "first_name": "Eben",
      "last_name": "McQuirter",
      "email": "",
      "is_staff": false,
      "is_active": true,
      "date_joined": "2018-03-28T01:07:07.876Z",
      "groups": [
        1
      ],
      "user_permissions": []
    }
  },
  {
    "model": "auth.user",
    "pk": 66,
    "fields": {
      "password": "pbkdf2_sha256$36000$08mhYXA6J4tI$yD5iB1ITo+SZcDok5Y/+fhzRW9GefZ/F1dOT5de20QI=",
      "last_login": null,
      "is_superuser": false,
      "username": "BKlinerNone",
      "first_name": "Burke",
      "last_name": "Kliner",
      "email": "",
      "is_staff": false,
      "is_active": true,
      "date_joined": "2018-03-28T01:07:07.958Z",
      "groups": [
        1
      ],
      "user_permissions": []
    }
  },
  {
    "model": "auth.user",
    "pk": 67,
    "fields": {
      "password": "pbkdf2_sha256$36000$PcATc46HZ5dT$6qK9lFvjoduBIFCPuHgc20cCqYQKozXm9A8oSB6thAM=",
      "last_login": null,
      "is_superuser": false,
      "username": "BChallaceNone",
      "first_name": "Beaufort",
      "last_name": "Challace",
      "email": "",
      "is_staff": false,
      "is_active": true,
      "date_joined": "2018-03-28T01:07:08.021Z",
      "groups": [
        1
      ],
      "user_permissions": []
    }
  },
  {
    "model": "auth.user",
    "pk": 68,
    "fields": {
      "password": "pbkdf2_sha256$36000$7f98E1HMQv79$JDrSgpZohAwrPccsltgKeMooGs+Ybw9rrs5cmOf2b2w=",
      "last_login": null,
      "is_superuser": false,
      "username": "GBritcherNone",
      "first_name": "Gratia",
      "last_name": "Britcher",
      "email": "",
      "is_staff": false,
      "is_active": true,
      "date_joined": "2018-03-28T01:07:08.084Z",
      "groups": [
        1
      ],
      "user_permissions": []
    }
  },
  {
    "model": "auth.user",
    "pk": 69,
    "fields": {
      "password": "pbkdf2_sha256$36000$dRKSdt4EfVOU$rj0eqbLR7nze2zH7BrClhgLMVKHGAlpj57Sn/eGKXqg=",
      "last_login": null,
      "is_superuser": false,
      "username": "ECrinsonNone",
      "first_name": "Emyle",
      "last_name": "Crinson",
      "email": "",
      "is_staff": false,
      "is_active": true,
      "date_joined": "2018-03-28T01:07:08.144Z",
      "groups": [
        1
      ],
      "user_permissions": []
    }
  },
  {
    "model": "auth.user",
    "pk": 70,
    "fields": {
      "password": "pbkdf2_sha256$36000$btjKpQjX973s$JJpd0ZEPug52tV32xgJzlCi1hIqBp2NJaR9JuqPW20Q=",
      "last_login": null,
      "is_superuser": false,
      "username": "EFalkNone",
      "first_name": "Emmalynn",
      "last_name": "Falk",
      "email": "",
      "is_staff": false,
      "is_active": true,
      "date_joined": "2018-03-28T01:07:08.214Z",
      "groups": [
        1
      ],
      "user_permissions": []
    }
  },
  {
    "model": "auth.user",
    "pk": 71,
    "fields": {
      "password": "pbkdf2_sha256$36000$KyUy2XUbyVCj$RjTmKY59yafiYmadAV+9lpFxqa3MWUQJv1KKLhggCus=",
      "last_login": null,
      "is_superuser": false,
      "username": "BO'DyvoyNone",
      "first_name": "Blondell",
      "last_name": "O'Dyvoy",
      "email": "",
      "is_staff": false,
      "is_active": true,
      "date_joined": "2018-03-28T01:07:08.275Z",
      "groups": [
        1
      ],
      "user_permissions": []
    }
  },
  {
    "model": "auth.user",
    "pk": 72,
    "fields": {
      "password": "pbkdf2_sha256$36000$StZsRoFajmV0$49fCY2aIN/OPrzCYvOWIRQjII+sFvuWq/Klb5UHzOG8=",
      "last_login": null,
      "is_superuser": false,
      "username": "GTowseyNone",
      "first_name": "Geoffrey",
      "last_name": "Towsey",
      "email": "",
      "is_staff": false,
      "is_active": true,
      "date_joined": "2018-03-28T01:07:08.347Z",
      "groups": [
        1
      ],
      "user_permissions": []
    }
  },
  {
    "model": "auth.user",
    "pk": 73,
    "fields": {
      "password": "pbkdf2_sha256$36000$EL3JtUJzYngs$UpY0EjLjkIRsrGCfFjyAsEOjJAM5LP2V9hU9OeHMm6s=",
      "last_login": null,
      "is_superuser": false,
      "username": "JDymidowskiNone",
      "first_name": "Jedd",
      "last_name": "Dymidowski",
      "email": "",
      "is_staff": false,
      "is_active": true,
      "date_joined": "2018-03-28T01:07:08.430Z",
      "groups": [
        1
      ],
      "user_permissions": []
    }
  },
  {
    "model": "auth.user",
    "pk": 74,
    "fields": {
      "password": "pbkdf2_sha256$36000$5EpuJj6Wet17$v0sj0NLS3MDyti8U3YW1FfHiH+93ZZN2y4LXG1O+OaE=",
      "last_login": null,
      "is_superuser": false,
      "username": "TFarrallNone",
      "first_name": "Tiena",
      "last_name": "Farrall",
      "email": "",
      "is_staff": false,
      "is_active": true,
      "date_joined": "2018-03-28T01:07:08.514Z",
      "groups": [
        1
      ],
      "user_permissions": []
    }
  },
  {
    "model": "auth.user",
    "pk": 75,
    "fields": {
      "password": "pbkdf2_sha256$36000$drjL18zayYwV$kXtl37G2wZR1Zmhnt4fRU1jo7ednfY1GUEghS5l+xD8=",
      "last_login": null,
      "is_superuser": false,
      "username": "BBisonNone",
      "first_name": "Blisse",
      "last_name": "Bison",
      "email": "",
      "is_staff": false,
      "is_active": true,
      "date_joined": "2018-03-28T01:07:08.576Z",
      "groups": [
        1
      ],
      "user_permissions": []
    }
  },
  {
    "model": "auth.user",
    "pk": 76,
    "fields": {
      "password": "pbkdf2_sha256$36000$Kmjm77PzkCly$q/S9S75QRUBFYs4G+H90cKvK0eBEyrPA6MzRPlbZyTQ=",
      "last_login": null,
      "is_superuser": false,
      "username": "AFreethNone",
      "first_name": "Agosto",
      "last_name": "Freeth",
      "email": "",
      "is_staff": false,
      "is_active": true,
      "date_joined": "2018-03-28T01:07:08.648Z",
      "groups": [
        1
      ],
      "user_permissions": []
    }
  },
  {
    "model": "auth.user",
    "pk": 77,
    "fields": {
      "password": "pbkdf2_sha256$36000$82Wihug6ESPO$2bSRfeBKyE6J7fknH+GiUGvrTgdakXxhsGHQLdoZGJM=",
      "last_login": null,
      "is_superuser": false,
      "username": "TYacobsohnNone",
      "first_name": "Tabby",
      "last_name": "Yacobsohn",
      "email": "",
      "is_staff": false,
      "is_active": true,
      "date_joined": "2018-03-28T01:07:08.711Z",
      "groups": [
        1
      ],
      "user_permissions": []
    }
  },
  {
    "model": "auth.user",
    "pk": 78,
    "fields": {
      "password": "pbkdf2_sha256$36000$fDEEG4FDtu9r$EfIxcB8QElE+t0VcuZRkOM47NH3ITLuMqt44DdpL0u0=",
      "last_login": null,
      "is_superuser": false,
      "username": "GOliffNone",
      "first_name": "Gregorius",
      "last_name": "Oliff",
      "email": "",
      "is_staff": false,
      "is_active": true,
      "date_joined": "2018-03-28T01:07:08.770Z",
      "groups": [
        1
      ],
      "user_permissions": []
    }
  },
  {
    "model": "auth.user",
    "pk": 79,
    "fields": {
      "password": "pbkdf2_sha256$36000$K9vUhtbo7UAS$3ZApZfXNweJa4DHYu9K5bKToQ4RUUE4ope95OTYzXOw=",
      "last_login": null,
      "is_superuser": false,
      "username": "MCoatsNone",
      "first_name": "Meryl",
      "last_name": "Coats",
      "email": "",
      "is_staff": false,
      "is_active": true,
      "date_joined": "2018-03-28T01:07:08.845Z",
      "groups": [
        1
      ],
      "user_permissions": []
    }
  },
  {
    "model": "auth.user",
    "pk": 80,
    "fields": {
      "password": "pbkdf2_sha256$36000$DBn6vfcdY98Z$eOsyQPOjd40fPhGGjshQ8HgFH3snGkQfAbq4E2/XeJA=",
      "last_login": null,
      "is_superuser": false,
      "username": "RSergeauntNone",
      "first_name": "Robbyn",
      "last_name": "Sergeaunt",
      "email": "",
      "is_staff": false,
      "is_active": true,
      "date_joined": "2018-03-28T01:07:08.927Z",
      "groups": [
        1
      ],
      "user_permissions": []
    }
  },
  {
    "model": "auth.user",
    "pk": 81,
    "fields": {
      "password": "pbkdf2_sha256$36000$t9fhmEcMr8a0$CJPEKP/YMR6DA7Ib/As4jwtnsfJiQ2TK4M+8beFVTW4=",
      "last_login": null,
      "is_superuser": false,
      "username": "KFontanetNone",
      "first_name": "Kristos",
      "last_name": "Fontanet",
      "email": "",
      "is_staff": false,
      "is_active": true,
      "date_joined": "2018-03-28T01:07:08.994Z",
      "groups": [
        1
      ],
      "user_permissions": []
    }
  },
  {
    "model": "auth.user",
    "pk": 82,
    "fields": {
      "password": "pbkdf2_sha256$36000$2oYUV7iUhPvm$FJbKIGkuyYumymXvNObMBTJuSsWzzqa39PMdiSymZUw=",
      "last_login": null,
      "is_superuser": false,
      "username": "PRiccardiNone",
      "first_name": "Paola",
      "last_name": "Riccardi",
      "email": "",
      "is_staff": false,
      "is_active": true,
      "date_joined": "2018-03-28T01:07:09.066Z",
      "groups": [
        1
      ],
      "user_permissions": []
    }
  }
]